prolog/__init__.py
prolog/predicate.py
prolog/prolog.py
prolog/swipl/__init__.py
prolog/swipl/exception.py
prolog/swipl/swipl.py
prolog/swipl/syntax.py
prolog_interface-0.2.dist-info/LICENSE
prolog_interface-0.2.dist-info/WHEEL
prolog_interface-0.2.dist-info/METADATA
prolog_interface-0.2.dist-info/RECORD
