Metadata-Version: 2.1
Name: prolog-interface
Version: 0.2
Summary: Keep it easy! Swi-Prolog object-oriented interface for humans.
License: MIT
Author: timoniq
Requires-Python: >=3.7,<4.0
Classifier: License :: OSI Approved :: MIT License
Classifier: Programming Language :: Python :: 3
Classifier: Programming Language :: Python :: 3.7
Classifier: Programming Language :: Python :: 3.8
Requires-Dist: pexpect (>=4.8.0,<5.0.0)
